odoo/addons/website_sale_coupon_restrict/README.rst
odoo/addons/website_sale_coupon_restrict/__init__.py
odoo/addons/website_sale_coupon_restrict/__manifest__.py
odoo/addons/website_sale_coupon_restrict/i18n/es.po
odoo/addons/website_sale_coupon_restrict/i18n/website_sale_coupon_restrict.pot
odoo/addons/website_sale_coupon_restrict/models/__init__.py
odoo/addons/website_sale_coupon_restrict/models/sale_coupon.py
odoo/addons/website_sale_coupon_restrict/models/sale_coupon_program.py
odoo/addons/website_sale_coupon_restrict/readme/CONFIGURE.rst
odoo/addons/website_sale_coupon_restrict/readme/CONTRIBUTORS.rst
odoo/addons/website_sale_coupon_restrict/readme/DESCRIPTION.rst
odoo/addons/website_sale_coupon_restrict/readme/USAGE.rst
odoo/addons/website_sale_coupon_restrict/static/description/icon.png
odoo/addons/website_sale_coupon_restrict/static/description/index.html
odoo/addons/website_sale_coupon_restrict/tests/__init__.py
odoo/addons/website_sale_coupon_restrict/tests/test_website_sale_coupon_restrict.py
odoo/addons/website_sale_coupon_restrict/views/sale_coupon_program_views.xml
odoo13_addon_website_sale_coupon_restrict-13.0.1.0.1.dev4.dist-info/METADATA
odoo13_addon_website_sale_coupon_restrict-13.0.1.0.1.dev4.dist-info/WHEEL
odoo13_addon_website_sale_coupon_restrict-13.0.1.0.1.dev4.dist-info/top_level.txt
odoo13_addon_website_sale_coupon_restrict-13.0.1.0.1.dev4.dist-info/RECORD
